byted_pyzeebe/__init__.py
byted_pyzeebe-0.0.1.dist-info/METADATA
byted_pyzeebe-0.0.1.dist-info/WHEEL
byted_pyzeebe-0.0.1.dist-info/top_level.txt
byted_pyzeebe-0.0.1.dist-info/RECORD
